PC_Utils/Datetime.py
PC_Utils/FileManagement.py
PC_Utils/FileManagement_w_Azure.py
PC_Utils/ObtainEmails.py
PC_Utils/Runtime.py
PC_Utils/__init__.py
PC_Utils/_version.py
pc_utils-0.1.0.post9.dist-info/LICENSE
pc_utils-0.1.0.post9.dist-info/METADATA
pc_utils-0.1.0.post9.dist-info/WHEEL
pc_utils-0.1.0.post9.dist-info/top_level.txt
pc_utils-0.1.0.post9.dist-info/RECORD
