Metadata-Version: 2.2
Name: PC_Utils
Version: 0.1.0.post9
Summary: This package includes utility modules for datetime handling, file management, runtime tracking, etc.
Author-email: "Marcos E. Mercado" <marcos_elias@hotmail.com>
Keywords: utilities,files,runtime,datetime,Azure
Classifier: Programming Language :: Python :: 3
Classifier: License :: OSI Approved :: MIT License
Classifier: Operating System :: OS Independent
Requires-Python: >=3.8
License-File: LICENSE
